README
setup.cfg
setup.py
pyahooapis/__init__.py
pyahooapis/service.py
pyahooapis/utils.py
pyahooapis.egg-info/PKG-INFO
pyahooapis.egg-info/SOURCES.txt
pyahooapis.egg-info/dependency_links.txt
pyahooapis.egg-info/entry_points.txt
pyahooapis.egg-info/not-zip-safe
pyahooapis.egg-info/requires.txt
pyahooapis.egg-info/top_level.txt
pyahooapis/jlp/__init__.py
pyahooapis/jlp/daservice.py
pyahooapis/jlp/furiganaservice.py
pyahooapis/jlp/jimservice.py
pyahooapis/jlp/keyphraseservice.py
pyahooapis/jlp/kouseiservice.py
pyahooapis/jlp/maservice.py