Metadata-Version: 1.0
Name: pyahooapis
Version: 0.2.3
Summary: Yahoo! Japan Text APIs Python wrapper
Home-page: https://github.com/ukyo/pyahooapis
Author: ukyo
Author-email: ukyo.web@gmail.com
License: Apache License 2.0
Keywords: yahoo text jlp
Platform: UNKNOWN
